django_static_ace_builds/.DS_Store
django_static_ace_builds/__init__.py
django_static_ace_builds/admin.py
django_static_ace_builds/apps.py
django_static_ace_builds/models.py
django_static_ace_builds/tests.py
django_static_ace_builds/views.py
django_static_ace_builds/migrations/__init__.py
django_static_ace_builds/static/.DS_Store
django_static_ace_builds/static/ace-builds/.DS_Store
django_static_ace_builds/static/ace-builds/ace.js
django_static_ace_builds/static/ace-builds/ext-beautify.js
django_static_ace_builds/static/ace-builds/ext-code_lens.js
django_static_ace_builds/static/ace-builds/ext-elastic_tabstops_lite.js
django_static_ace_builds/static/ace-builds/ext-emmet.js
django_static_ace_builds/static/ace-builds/ext-error_marker.js
django_static_ace_builds/static/ace-builds/ext-hardwrap.js
django_static_ace_builds/static/ace-builds/ext-keybinding_menu.js
django_static_ace_builds/static/ace-builds/ext-language_tools.js
django_static_ace_builds/static/ace-builds/ext-linking.js
django_static_ace_builds/static/ace-builds/ext-modelist.js
django_static_ace_builds/static/ace-builds/ext-options.js
django_static_ace_builds/static/ace-builds/ext-prompt.js
django_static_ace_builds/static/ace-builds/ext-rtl.js
django_static_ace_builds/static/ace-builds/ext-searchbox.js
django_static_ace_builds/static/ace-builds/ext-settings_menu.js
django_static_ace_builds/static/ace-builds/ext-spellcheck.js
django_static_ace_builds/static/ace-builds/ext-split.js
django_static_ace_builds/static/ace-builds/ext-static_highlight.js
django_static_ace_builds/static/ace-builds/ext-statusbar.js
django_static_ace_builds/static/ace-builds/ext-textarea.js
django_static_ace_builds/static/ace-builds/ext-themelist.js
django_static_ace_builds/static/ace-builds/ext-whitespace.js
django_static_ace_builds/static/ace-builds/keybinding-emacs.js
django_static_ace_builds/static/ace-builds/keybinding-sublime.js
django_static_ace_builds/static/ace-builds/keybinding-vim.js
django_static_ace_builds-1.5.0.1.dist-info/licenses/LICENSE
django_static_ace_builds-1.5.0.1.dist-info/METADATA
django_static_ace_builds-1.5.0.1.dist-info/WHEEL
django_static_ace_builds-1.5.0.1.dist-info/top_level.txt
django_static_ace_builds-1.5.0.1.dist-info/RECORD
