Metadata-Version: 2.4
Name: django-static-ace-builds
Version: 1.5.0.1
Summary: Django application contain ace-builds(Ajax.org Cloud9 Editor) static files.
Author: rRR0VrFP
Maintainer: rRR0VrFP
License: MIT
Keywords: django-static-ace-builds
Classifier: Development Status :: 5 - Production/Stable
Classifier: Intended Audience :: Developers
Classifier: Topic :: Software Development :: Libraries :: Python Modules
Classifier: License :: OSI Approved :: MIT License
Classifier: Programming Language :: Python :: 3
Classifier: Programming Language :: Python :: 3 :: Only
License-File: LICENSE
Dynamic: author
Dynamic: classifier
Dynamic: description
Dynamic: description-content-type
Dynamic: keywords
Dynamic: license
Dynamic: license-file
Dynamic: maintainer
Dynamic: summary
